counter.v
/********counter module *******/
    module counter (
                      input                   clk    ,     
                      output                  stop
    );
    //intialize counter to zero 
    integer  counter =0;
    assign stop = (counter >=4'b1000) ;
    always @(posedge clk) begin
        if (counter != 4'b1000) begin
           counter <= counter + 4'b0001 ; 
        end 
    end
    
    endmodule

shift.v
/*******shift module *******/
    module shift (
    input                                    clk         ,
    input                                    D           ,
    input                                    rst         ,
    input                                    rst_data    ,
    output       reg                         Q
    );
    always @(posedge clk , negedge rst) begin
        if (!rst) begin
            Q <= rst_data ;
        end else begin
            Q <= D ; 
        end
       
    end
    endmodule

upper.v
    module upper (
    input  [3:0]                        seed                   ,
    input                               clk                    ,
    input                               rst                    ,
    output [3:0]                        OUT_allbits
    );
    
    wire D1;
    wire D2;
    wire D3;
    wire D4;
    wire Q1;
    wire Q2;
    wire Q3;
    wire Q4;
    wire xor_out;
    assign xor_out     = Q3 ^ Q4         ;
    assign D1          = xor_out ^ Q2    ;
    assign D2          = Q1              ;
    assign D3          = Q2              ;
    assign D4          = Q3              ;
    assign OUT_allbits = {Q1,Q2,Q3,Q4}   ;
    shift shift1 (
        .clk(clk),
        .rst(rst),
        .rst_data(seed[0]),
        .D(D1),
        .Q(Q1)

    );
    shift shift2 (
        .clk(clk),
        .rst(rst),
        .rst_data(seed[1]),
        .D(D2),
        .Q(Q2)
    );
    shift shift3(
        .clk(clk),
        .rst(rst),
        .rst_data(seed[2]),
        .D(D3),
        .Q(Q3)
    );
    shift shift4(
        .clk(clk),
        .rst(rst),
        .rst_data(seed[3]),
        .D(D4),
        .Q(Q4)
    );
    endmodule

top.v
/******top module ***********/
    module top (
    input                                                rst     ,
    input                                                clk     ,
    input        [3:0]                                   seed    ,
    output                      reg                      OUT     ,
    output                      reg                      vaild

    );
    //internal signals
    wire [3:0]   OUT_allbits ;
    reg  [3:0]   All_out     ;
    wire         stop        ;
    //integer for loop
    integer      i = 0       ;   
    always @(posedge stop) begin
        if (stop) begin
            vaild   <=   1'b1           ;
            All_out =   OUT_allbits     ;
        end
    end
    always @(posedge vaild ) begin
        for (i = 1'b0;i<4 ;i=i+1'b1 ) begin
       @(posedge clk) OUT <= All_out[i] ; 
   end
    end
   
  
    upper upper1(
    .clk(clk),
    .rst(rst),
    .seed(seed),
    .OUT_allbits(OUT_allbits)
    );

    counter counter1(
        .clk(clk),
        .stop(stop)
    );
    
    endmodule

top_tb.v
/*************test bench ***********/
    `timescale 1ns/1ns
    module top_tb (
    );

    reg                       clk_tb      ;
    reg                       rst_tb      ;
    reg               [3:0]   seed_tb     ;
    wire                      OUT_tb      ;
    wire                      vaild_tb    ;

    parameter CLOCK_PERIOD = 10 ;
    parameter HALF_CLOCK   = CLOCK_PERIOD / 2 ;
    initial begin
        $dumpfile("LFSR.vcd");
        $dumpvars;
        clk_tb = 0       ;
        rst_tb = 0       ;
        seed_tb = 4'b1001;
        DUT.vaild = 0    ;
        DUT.i = 0        ;
        #3
        rst_tb = 1 ;
        #4
        /******* CYCLE 1**********/
        $display ("out = %0b",DUT.OUT_allbits);
        if (DUT.OUT_allbits == 4'b1100) begin
            $display("test 1 passed");
        end else begin
            $display("test 1 failed");
        end
        /******* CYCLE 2**********/
        #CLOCK_PERIOD
        if (DUT.OUT_allbits == 4'b1110) begin
            $display("test 2 passed");
        end else begin
            $display("test 2 failed");
        end
        /******* CYCLE 3**********/
        #CLOCK_PERIOD
        if (DUT.OUT_allbits == 4'b0111) begin
            $display("test 3 passed");
        end else begin
            $display("test 3 failed");
        end
        /******* CYCLE 4**********/ 
        #CLOCK_PERIOD
        if (DUT.OUT_allbits == 4'b1011) begin
            $display("test 4 passed");
        end else begin
            $display("test 4 failed");
        end
        /******* CYCLE 5**********/
        #CLOCK_PERIOD
        if (DUT.OUT_allbits == 4'b0101) begin
            $display("test 5 passed");
        end else begin
            $display("test 5 failed");
        end
        /******* CYCLE 6**********/
        #CLOCK_PERIOD
        if (DUT.OUT_allbits == 4'b0010) begin
            $display("test 6 passed");
        end else begin
            $display("test 6 failed");
        end
        /******* CYCLE 7**********/
        #CLOCK_PERIOD
        if (DUT.OUT_allbits == 4'b1001) begin
            $display("test 7 passed");
        end else begin
            $display("test 7 failed");
        end
        /******* CYCLE 8**********/
        #CLOCK_PERIOD
        if (DUT.OUT_allbits == 4'b1100) begin
            $display("test 8 passed");
        end else begin
            $display("test 8 failed");
        end
        

        #CLOCK_PERIOD
        if (OUT_tb == 1'b0) begin
            $display("test 9 passed");
        end else begin
            $display("test 9 failed");
        end
        #CLOCK_PERIOD
         if (OUT_tb == 1'b0) begin
            $display("test 10 passed");
        end else begin
            $display("test 10 failed");
        end
        #CLOCK_PERIOD
        if (OUT_tb == 1'b1) begin
            $display("test 11 passed");
        end else begin
            $display("test 11 failed");
        end
        #CLOCK_PERIOD
        if (OUT_tb == 1'b1) begin
            $display("test 12 passed");
        end else begin
            $display("test 12 failed");
        end
        #100
        $finish;
        
        
    end

    always #HALF_CLOCK clk_tb = ~ clk_tb ;
    top DUT (
                .clk(clk_tb),
                .rst(rst_tb),
                .seed(seed_tb),
                .OUT(OUT_tb),
                .vaild(vaild_tb)
    );
    endmodule

LFSR.vcd
$date
	Thu Mar 17 17:31:47 2022
$end
$version
	ModelSim Version 10.5b
$end
$timescale
	1ns
$end

$scope module top_tb $end
$var parameter 32 ! CLOCK_PERIOD $end
$var parameter 32 " HALF_CLOCK $end
$var reg 1 # clk_tb $end
$var reg 1 $ rst_tb $end
$var reg 4 % seed_tb [3:0] $end
$var wire 1 & OUT_tb $end
$var wire 1 ' vaild_tb $end

$scope module DUT $end
$var wire 1 ( rst $end
$var wire 1 ) clk $end
$var wire 1 * seed [3] $end
$var wire 1 + seed [2] $end
$var wire 1 , seed [1] $end
$var wire 1 - seed [0] $end
$var reg 1 . OUT $end
$var reg 1 / vaild $end
$var wire 1 0 OUT_allbits [3] $end
$var wire 1 1 OUT_allbits [2] $end
$var wire 1 2 OUT_allbits [1] $end
$var wire 1 3 OUT_allbits [0] $end
$var reg 4 4 All_out [3:0] $end
$var wire 1 5 stop $end
$var integer 32 6 i $end

$scope module upper1 $end
$var wire 1 * seed [3] $end
$var wire 1 + seed [2] $end
$var wire 1 , seed [1] $end
$var wire 1 - seed [0] $end
$var wire 1 ) clk $end
$var wire 1 ( rst $end
$var wire 1 0 OUT_allbits [3] $end
$var wire 1 1 OUT_allbits [2] $end
$var wire 1 2 OUT_allbits [1] $end
$var wire 1 3 OUT_allbits [0] $end
$var wire 1 7 D1 $end
$var wire 1 8 D2 $end
$var wire 1 9 D3 $end
$var wire 1 : D4 $end
$var wire 1 ; Q1 $end
$var wire 1 < Q2 $end
$var wire 1 = Q3 $end
$var wire 1 > Q4 $end
$var wire 1 ? xor_out $end

$scope module shift1 $end
$var wire 1 ) clk $end
$var wire 1 7 D $end
$var wire 1 ( rst $end
$var wire 1 - rst_data $end
$var reg 1 @ Q $end
$upscope $end

$scope module shift2 $end
$var wire 1 ) clk $end
$var wire 1 8 D $end
$var wire 1 ( rst $end
$var wire 1 , rst_data $end
$var reg 1 A Q $end
$upscope $end

$scope module shift3 $end
$var wire 1 ) clk $end
$var wire 1 9 D $end
$var wire 1 ( rst $end
$var wire 1 + rst_data $end
$var reg 1 B Q $end
$upscope $end

$scope module shift4 $end
$var wire 1 ) clk $end
$var wire 1 : D $end
$var wire 1 ( rst $end
$var wire 1 * rst_data $end
$var reg 1 C Q $end
$upscope $end
$upscope $end

$scope module counter1 $end
$var wire 1 ) clk $end
$var wire 1 5 stop $end
$var integer 32 D counter $end
$upscope $end
$upscope $end
$upscope $end
$enddefinitions $end
#0
$dumpvars
0#
0$
b1001 %
x.
0/
bx 4
1@
0A
0B
1C
b1010 !
b101 "
b0 6
b0 D
x&
0'
13
02
01
10
05
17
18
09
0:
1;
0<
0=
1>
1?
1-
0,
0+
1*
0(
0)
$end
#3
1$
1(
#5
1#
1)
1A
0C
b1 D
1<
0>
0?
19
03
11
#10
0#
0)
#15
1#
1)
1B
b10 D
1=
1?
1:
07
12
#20
0#
0)
#25
1#
1)
0@
1C
b11 D
0;
1>
0?
08
17
13
00
#30
0#
0)
#35
1#
1)
1@
0A
b100 D
1;
0<
07
09
18
01
10
#40
0#
0)
#45
1#
1)
0@
1A
0B
b101 D
0;
1<
0=
1?
0:
19
08
02
11
00
#50
0#
0)
#55
1#
1)
0A
1B
0C
b110 D
0<
1=
0>
1:
17
09
03
12
01
#60
0#
0)
#65
1#
1)
1@
0B
1C
b111 D
1;
0=
1>
0:
18
13
02
10
#70
0#
0)
#75
1#
1)
1A
0C
b1000 D
1<
0>
0?
19
03
11
15
b1100 4
1/
1'
#80
0#
0)
#85
1#
1)
b1 6
1B
0.
1=
0&
1?
1:
07
12
#90
0#
0)
#95
1#
1)
b10 6
0@
1C
0;
1>
0?
08
17
13
00
#100
0#
0)
#105
1#
1)
b11 6
1@
0A
1.
1;
0<
1&
07
09
18
01
10
#110
0#
0)
#115
1#
1)
b100 6
0@
1A
0B
0;
1<
0=
1?
0:
19
08
02
11
00
#120
0#
0)
#125
1#
1)
0A
1B
0C
0<
1=
0>
1:
17
09
03
12
01
#130
0#
0)
#135
1#
1)
1@
0B
1C
1;
0=
1>
0:
18
13
02
10
#140
0#
0)
#145
1#
1)
1A
0C
1<
0>
0?
19
03
11
#150
0#
0)
#155
1#
1)
1B
1=
1?
1:
07
12
#160
0#
0)
#165
1#
1)
0@
1C
0;
1>
0?
08
17
13
00
#170
0#
0)
#175
1#
1)
1@
0A
1;
0<
07
09
18
01
10
#180
0#
0)
#185
1#
1)
0@
1A
0B
0;
1<
0=
1?
0:
19
08
02
11
00
#190
0#
0)
#195
1#
1)
0A
1B
0C
0<
1=
0>
1:
17
09
03
12
01
#200
0#
0)
#205
1#
1)
1@
0B
1C
1;
0=
1>
0:
18
13
02
10
#210
0#
0)
#215
1#
1)
1A
0C
1<
0>
0?
19
03
11
